odoo9_addon_mrp_production_unreserve-9.0.1.0.0.99.dev3-py2.7-nspkg.pth
odoo9_addon_mrp_production_unreserve-9.0.1.0.0.99.dev3.dist-info/METADATA
odoo9_addon_mrp_production_unreserve-9.0.1.0.0.99.dev3.dist-info/RECORD
odoo9_addon_mrp_production_unreserve-9.0.1.0.0.99.dev3.dist-info/WHEEL
odoo9_addon_mrp_production_unreserve-9.0.1.0.0.99.dev3.dist-info/namespace_packages.txt
odoo9_addon_mrp_production_unreserve-9.0.1.0.0.99.dev3.dist-info/top_level.txt
odoo_addons/mrp_production_unreserve/README.rst
odoo_addons/mrp_production_unreserve/__init__.py
odoo_addons/mrp_production_unreserve/__openerp__.py
odoo_addons/mrp_production_unreserve/data/mrp_workflow.xml
odoo_addons/mrp_production_unreserve/i18n/mrp_production_unreserve.pot
odoo_addons/mrp_production_unreserve/models/__init__.py
odoo_addons/mrp_production_unreserve/models/mrp_production.py
odoo_addons/mrp_production_unreserve/static/description/icon.png
odoo_addons/mrp_production_unreserve/tests/__init__.py
odoo_addons/mrp_production_unreserve/tests/test_mrp_production_unreserve.py
odoo_addons/mrp_production_unreserve/views/mrp_production_view.xml
